locojson/__init__.py
locojson/core.py
locojson/py.typed
locojson-0.2.1.dist-info/LICENSE
locojson-0.2.1.dist-info/METADATA
locojson-0.2.1.dist-info/WHEEL
locojson-0.2.1.dist-info/RECORD
